mytk/__init__.py
mytk/__main__.py
mytk/app.py
mytk/base.py
mytk/bindable.py
mytk/button.py
mytk/canvasview.py
mytk/checkbox.py
mytk/controls.py
mytk/dataviews.py
mytk/dialog.py
mytk/entries.py
mytk/eventcapable.py
mytk/figures.py
mytk/fileviewer.py
mytk/images.py
mytk/indicators.py
mytk/labels.py
mytk/modulesmanager.py
mytk/notificationcenter.py
mytk/popupmenu.py
mytk/radiobutton.py
mytk/tableview.py
mytk/tabulardata.py
mytk/utils.py
mytk/vectors.py
mytk/videoview.py
mytk/views.py
mytk/window.py
mytk/example_apps/__init__.py
mytk/example_apps/canvas_app.py
mytk/example_apps/controlpanel_app.py
mytk/example_apps/example.py
mytk/example_apps/file_calculator_app.py
mytk/example_apps/fileviewer_app.py
mytk/example_apps/filters_app.py
mytk/example_apps/lensviewer_app.py
mytk/example_apps/microscope_app.py
mytk/example_apps/powermeter_app.py
mytk/example_apps/pydatagraph_app.py
mytk/lab/tklab.py
mytk/resources/error.png
mytk/resources/info.png
mytk/resources/warning.png
mytk/tests/envtest.py
mytk/tests/testBaseWidgets.py
mytk/tests/testBindings.py
mytk/tests/testBox.py
mytk/tests/testButton.py
mytk/tests/testCanvasView.py
mytk/tests/testCheckbox.py
mytk/tests/testCustomDialogs.py
mytk/tests/testDialogs.py
mytk/tests/testEntries.py
mytk/tests/testImages.py
mytk/tests/testLabel.py
mytk/tests/testModulesManager.py
mytk/tests/testMyApp.py
mytk/tests/testNotificationCenter.py
mytk/tests/testPopupMenu.py
mytk/tests/testRadioButtons.py
mytk/tests/testSlider.py
mytk/tests/testStyles.py
mytk/tests/testTableView.py
mytk/tests/testTabularData.py
mytk/tests/testTreeData.py
mytk/tests/testTreeTableView.py
mytk/tests/testURLLabel.py
mytk/tests/testView.py
mytk-0.9.12.dist-info/LICENSE
mytk-0.9.12.dist-info/METADATA
mytk-0.9.12.dist-info/WHEEL
mytk-0.9.12.dist-info/top_level.txt
mytk-0.9.12.dist-info/RECORD
