Metadata-Version: 2.1
Name: mytk
Version: 0.9.12
Summary: A wrapper for Tkinter for busy scientists
Author-email: Daniel Côté <dccote@cervo.ulaval.ca>
Maintainer-email: Daniel Côté <dccote@cervo.ulaval.ca>
License: MIT License
Classifier: Development Status :: 3 - Alpha
Classifier: Topic :: Software Development :: Build Tools
Classifier: Programming Language :: Python :: 3
Classifier: Programming Language :: Python :: 3.12
License-File: LICENSE
Requires-Dist: matplotlib==3.9.2
Requires-Dist: numpy
Requires-Dist: packaging
Requires-Dist: pyperclip
Requires-Dist: Requests
Requires-Dist: scipy
Requires-Dist: pandas
Requires-Dist: openpyxl
Requires-Dist: raytracing
Requires-Dist: opencv-python
